bin/__init__.py
lsfmpy/__init__.py
lsfmpy/bdv.py
lsfmpy/constants.py
lsfmpy/dump_metadata.py
lsfmpy/export.py
lsfmpy/h5_external.py
lsfmpy/image.py
lsfmpy/lmdf.py
lsfmpy/lmdf_cli.py
lsfmpy/lsfm_info.py
lsfmpy/processing.py
lsfmpy/transforms.py
lsfmpy/utils.py
lsfmpy-0.1.0.data/scripts/dump_metadata
lsfmpy-0.1.0.data/scripts/lsfmpy
lsfmpy-0.1.0.data/scripts/lsfmpy_create_autocomplete
lsfmpy-0.1.0.dist-info/LICENSE
lsfmpy-0.1.0.dist-info/METADATA
lsfmpy-0.1.0.dist-info/WHEEL
lsfmpy-0.1.0.dist-info/top_level.txt
lsfmpy-0.1.0.dist-info/RECORD
