Metadata-Version: 2.1
Name: lsfmpy
Version: 0.1.0
Summary: HDF5-based software for storing and managing voluminous 3D imaging data
Home-page: https://github.com/Neuroinflab/lsfm_image_server
Author: Sylwia Bednarek, Piotr Majka
Author-email: s.bednarek@nencki.gov.pl
License: GPLv3
Platform: UNKNOWN
Classifier: Development Status :: 4 - Beta
Classifier: Programming Language :: Python :: 3.8
Classifier: License :: OSI Approved :: GNU General Public License v3 (GPLv3)
Classifier: Operating System :: POSIX :: Linux
Classifier: Intended Audience :: Science/Research
Classifier: Topic :: Scientific/Engineering
Classifier: Natural Language :: English
Classifier: Environment :: Console
Requires-Python: >=3.8
Requires-Dist: SimpleITK
Requires-Dist: enum34
Requires-Dist: fire
Requires-Dist: h5py
Requires-Dist: h5py-cache
Requires-Dist: imageio
Requires-Dist: lxml
Requires-Dist: nibabel
Requires-Dist: numpy
Requires-Dist: scipy
Requires-Dist: tifffile
